{
 "version": 1,
 "elements": {
  "0": {
   "id": 0,
   "name": "Al Azif",
   "origin": {
    "type": "Original",
    "author": {
     "type": "Character",
     "character": 18
    }
   },
   "date": {
    "type": "Decade",
    "decade": 73
   },
   "language": 7
  },
  "1": {
   "id": 1,
   "name": "Necronomicon",
   "origin": {
    "type": "Translation",
    "text": 0,
    "translator": {
     "type": "Character",
     "character": 19
    }
   },
   "date": {
    "type": "Decade",
    "decade": 95
   },
   "language": 5,
   "format": {
    "type": "Book",
    "pages": 400,
    "binding": {
     "type": "Coptic",
     "cover": {
      "color": "SaddleBrown",
      "material": 0
     },
     "sewingPattern": {
      "type": "Simple",
      "color": "Silver",
      "size": "Medium",
      "stitches": [
       "Kettle",
       "Kettle",
       "Kettle"
      ]
     }
    },
    "size": {
     "width": 130,
     "height": 200
    }
   }
  },
  "2": {
   "id": 2,
   "name": "Necronomicon",
   "origin": {
    "type": "Translation",
    "text": 1,
    "translator": {
     "type": "Undefined"
    }
   },
   "date": {
    "type": "Year",
    "year": 1227
   },
   "language": 6
  }
 }
}